llm_editor/__init__.py
llm_editor/agent.py
llm_editor/cli.py
llm_editor/config.py
llm_editor/pricing.py
llm_editor/pricing.yaml
llm_editor/utils.py
llm_editor-0.1.5.dist-info/licenses/LICENSE
llm_editor-0.1.5.dist-info/METADATA
llm_editor-0.1.5.dist-info/WHEEL
llm_editor-0.1.5.dist-info/entry_points.txt
llm_editor-0.1.5.dist-info/top_level.txt
llm_editor-0.1.5.dist-info/RECORD
