Metadata-Version: 2.4
Name: llm-editor
Version: 0.1.5
Summary: A CLI tool to edit and chat with files using LLMs
Home-page: https://github.com/gptabhinav/llm-editor
Author: Abhinav
License: MIT
Project-URL: Source, https://github.com/gptabhinav/llm-editor
Project-URL: Bug Tracker, https://github.com/gptabhinav/llm-editor/issues
License-File: LICENSE
Requires-Dist: openai
Requires-Dist: PyYAML
Requires-Dist: python-dotenv
Dynamic: author
Dynamic: description
Dynamic: description-content-type
Dynamic: home-page
Dynamic: license
Dynamic: license-file
Dynamic: project-url
Dynamic: requires-dist
Dynamic: summary
